cilantro_ee/__init__.py
cilantro_ee/constants/__init__.py
cilantro_ee/constants/batcher.py
cilantro_ee/constants/block.py
cilantro_ee/constants/conf.py
cilantro_ee/constants/db.py
cilantro_ee/constants/db_config.py
cilantro_ee/constants/masternode.py
cilantro_ee/constants/overlay_network.py
cilantro_ee/constants/ports.py
cilantro_ee/constants/protocol.py
cilantro_ee/constants/system_config.py
cilantro_ee/constants/test_suites.py
cilantro_ee/constants/testnet.py
cilantro_ee/constants/zmq_filters.py
cilantro_ee/contracts/__init__.py
cilantro_ee/contracts/submission.s.py
cilantro_ee/contracts/sync.py
cilantro_ee/contracts/genesis/__init__.py
cilantro_ee/contracts/genesis/currency.s.py
cilantro_ee/contracts/genesis/election_house.s.py
cilantro_ee/contracts/genesis/rewards.s.py
cilantro_ee/contracts/genesis/stamp_cost.s.py
cilantro_ee/contracts/genesis/vkbook.s.py
cilantro_ee/contracts/temp/__init__.py
cilantro_ee/contracts/temp/masternodes.s.py
cilantro_ee/core/__init__.py
cilantro_ee/core/canonical.py
cilantro_ee/core/epochs.py
cilantro_ee/core/nonces.py
cilantro_ee/core/rewards.py
cilantro_ee/core/top.py
cilantro_ee/core/logger/__init__.py
cilantro_ee/core/logger/base.py
cilantro_ee/core/messages/__init__.py
cilantro_ee/core/messages/message.py
cilantro_ee/core/messages/message_type.py
cilantro_ee/core/messages/notification.py
cilantro_ee/nodes/__init__.py
cilantro_ee/nodes/base.py
cilantro_ee/nodes/catchup.py
cilantro_ee/nodes/state_sync.py
cilantro_ee/nodes/delegate/__init__.py
cilantro_ee/nodes/delegate/block_manager.py
cilantro_ee/nodes/delegate/delegate.py
cilantro_ee/nodes/delegate/sub_block_builder.py
cilantro_ee/nodes/delegate/sub_block_builder_manager.py
cilantro_ee/nodes/masternode/__init__.py
cilantro_ee/nodes/masternode/block_aggregator.py
cilantro_ee/nodes/masternode/block_contender.py
cilantro_ee/nodes/masternode/masternode.py
cilantro_ee/nodes/masternode/transaction_batcher.py
cilantro_ee/nodes/masternode/webserver.py
cilantro_ee/services/__init__.py
cilantro_ee-0.0.4.dist-info/LICENSE.txt
cilantro_ee-0.0.4.dist-info/METADATA
cilantro_ee-0.0.4.dist-info/WHEEL
cilantro_ee-0.0.4.dist-info/entry_points.txt
cilantro_ee-0.0.4.dist-info/top_level.txt
cilantro_ee-0.0.4.dist-info/RECORD
