Metadata-Version: 2.1
Name: cilantro-ee
Version: 0.0.4
Summary: Lamden Blockchain
Home-page: https://github.com/Lamden/cilantro-enterprise
Author: Lamden
Author-email: team@lamden.io
License: UNKNOWN
Platform: UNKNOWN
Classifier: Programming Language :: Python :: 3.6
Requires-Python: >=3.6.5
Requires-Dist: Cython (==0.29)
Requires-Dist: pycapnp (==0.6.3)
Requires-Dist: pyzmq (==17.0.0)
Requires-Dist: requests (==2.20.0)
Requires-Dist: uvloop (==0.9.1)
Requires-Dist: u-msgpack-python (==2.5.0)
Requires-Dist: yarl (==1.1.0)
Requires-Dist: contracting
Requires-Dist: click
Requires-Dist: simple-crypt
Requires-Dist: sanic (==19.6.3)
Requires-Dist: pymongo (==3.9)
Requires-Dist: rocks
Provides-Extra: dev
Requires-Dist: coloredlogs ; extra == 'dev'
Requires-Dist: coverage ; extra == 'dev'
Requires-Dist: numpy ; extra == 'dev'
Requires-Dist: scipy ; extra == 'dev'
Requires-Dist: vprof ; extra == 'dev'
Requires-Dist: paramiko ; extra == 'dev'
Requires-Dist: redis (==3.2.0) ; extra == 'dev'
Requires-Dist: simple-crypt (==4.1.7) ; extra == 'dev'
Requires-Dist: requests (==2.20.0) ; extra == 'dev'
Requires-Dist: uvloop (==0.9.1) ; extra == 'dev'
Requires-Dist: yarl (==1.1.0) ; extra == 'dev'
Requires-Dist: Click (==7.0) ; extra == 'dev'
Requires-Dist: sanic (==19.6.3) ; extra == 'dev'
Requires-Dist: sanic-limiter (==0.1.3) ; extra == 'dev'
Requires-Dist: Sanic-Cors (==0.9.9.post1) ; extra == 'dev'
Requires-Dist: secure ; extra == 'dev'
Requires-Dist: pathspec ; extra == 'dev'
Requires-Dist: umsgpack ; extra == 'dev'
Requires-Dist: aiohttp ; extra == 'dev'
